cli_formatter/__init__.py
cli_formatter/output_formatting/__init__.py
cli_formatter/output_formatting/output_formatter.py
cli_formatter/table_builder/__init__.py
cli_formatter/table_builder/table_builder.py
cli_formatter/table_builder/table_builder_alternative.py
cli_formatter/table_builder/table_formatter.py
cli_formatter-1.2.0.dist-info/LICENSE
cli_formatter-1.2.0.dist-info/METADATA
cli_formatter-1.2.0.dist-info/WHEEL
cli_formatter-1.2.0.dist-info/top_level.txt
cli_formatter-1.2.0.dist-info/RECORD
