Metadata-Version: 2.1
Name: cli-formatter
Version: 1.2.0
Summary: An utility for cli script to prettify their output
Home-page: https://github.com/wahlflo/cli-formatter
Author: Florian Wahl
Author-email: florian.wahl.developer@gmail.com
License: UNKNOWN
Platform: UNKNOWN
Classifier: Programming Language :: Python :: 3
Classifier: License :: OSI Approved :: MIT License
Classifier: Operating System :: OS Independent
Requires-Python: >=3.6
